core/__init__.py
core/titan_main.py
core/database/__init__.py
core/database/database.py
core/database/ohlcv_functions.py
core/markets/__init__.py
core/markets/market.py
core/markets/market_simulator.py
core/markets/market_watcher.py
core/markets/order.py
core/markets/position.py
core/markets/ticker.py
portfolio/__init__.py
portfolio/portfolio_manager.py
ta/__init__.py
ta/base_indicator.py
ta/bollinger_bands.py
ta/exponential_moving_average.py
ta/simple_moving_average.py
ta/volume_change_monitor.py
Titan_pro-1.2.1.dist-info/LICENSE
Titan_pro-1.2.1.dist-info/METADATA
Titan_pro-1.2.1.dist-info/WHEEL
Titan_pro-1.2.1.dist-info/top_level.txt
Titan_pro-1.2.1.dist-info/RECORD
